README.md
pyproject.toml
setup.py
osu2mp3/__init__.py
osu2mp3/__main__.py
osu2mp3/args.py
osu2mp3.egg-info/PKG-INFO
osu2mp3.egg-info/SOURCES.txt
osu2mp3.egg-info/dependency_links.txt
osu2mp3.egg-info/entry_points.txt
osu2mp3.egg-info/requires.txt
osu2mp3.egg-info/top_level.txt
osu2mp3/app/__init__.py
osu2mp3/app/app.py
osu2mp3/beatmap/__init__.py
osu2mp3/beatmap/beatmap.py
osu2mp3/progressbar/__init__.py
osu2mp3/progressbar/progressbar.py